miximaps/__init__.py
miximaps/census.py
miximaps/datacache.py
miximaps/nyc.py
miximaps/tiger.py
miximaps/ui.py
miximaps-0.1.3.dist-info/licenses/LICENSE
miximaps-0.1.3.dist-info/METADATA
miximaps-0.1.3.dist-info/WHEEL
miximaps-0.1.3.dist-info/top_level.txt
miximaps-0.1.3.dist-info/RECORD
